pencildraw/__init__.py
pencildraw/pencil_drawing.py
pencildraw/pencils/__init__.py
snowland_pencildraw-0.2.dist-info/LICENSE
snowland_pencildraw-0.2.dist-info/METADATA
snowland_pencildraw-0.2.dist-info/WHEEL
snowland_pencildraw-0.2.dist-info/top_level.txt
snowland_pencildraw-0.2.dist-info/RECORD
