Metadata-Version: 2.1
Name: snowland-pencildraw
Version: 0.2
Summary: pencils/pencil draw
Home-page: https://gitee.com/hoops/PencilDrawing_python3
Author: A.Star
Author-email: astar@snowland.ltd
Maintainer: A.Star
Maintainer-email: astar@snowland.ltd
License: BSD License
Platform: all
Classifier: Development Status :: 4 - Beta
Classifier: Operating System :: OS Independent
Classifier: Intended Audience :: Developers
Classifier: License :: OSI Approved :: BSD License
Classifier: Programming Language :: Python
Classifier: Programming Language :: Python :: Implementation
Classifier: Programming Language :: Python :: 3
Classifier: Programming Language :: Python :: 3.6
Classifier: Programming Language :: Python :: 3.7
Classifier: Programming Language :: Python :: 3.8
Classifier: Programming Language :: Python :: 3.9
Classifier: Programming Language :: Python :: 3.10
Classifier: Topic :: Software Development :: Libraries
License-File: LICENSE
Requires-Dist: scikit-image (>=0.14.0)
Requires-Dist: numpy (>=1.0.0)
Requires-Dist: scipy (>=0.14.0)
Requires-Dist: matplotlib (>=2.0.0)
Requires-Dist: astartool (>=0.0.8)
